.coveragerc
.gitignore
.travis.yml
LICENSE
MANIFEST.in
README
README.md
requirements.txt
setup.cfg
setup.py
twistd-autoreload.py
geventreactor/__init__.py
spinoff/__init__.py
spinoff.egg-info/PKG-INFO
spinoff.egg-info/SOURCES.txt
spinoff.egg-info/dependency_links.txt
spinoff.egg-info/entry_points.txt
spinoff.egg-info/requires.txt
spinoff.egg-info/top_level.txt
spinoff/actor/__init__.py
spinoff/actor/_actor.py
spinoff/actor/cell.py
spinoff/actor/context.py
spinoff/actor/events.py
spinoff/actor/exceptions.py
spinoff/actor/guardian.py
spinoff/actor/misc.py
spinoff/actor/node.py
spinoff/actor/props.py
spinoff/actor/quick.py
spinoff/actor/ref.py
spinoff/actor/runner.py
spinoff/actor/spin.py
spinoff/actor/typedref.py
spinoff/actor/uri.py
spinoff/actor/util.py
spinoff/actor/validate.py
spinoff/contrib/__init__.py
spinoff/contrib/timings.py
spinoff/contrib/filetransfer/__init__.py
spinoff/contrib/filetransfer/constants.py
spinoff/contrib/filetransfer/experimenting.py
spinoff/contrib/filetransfer/fileref.py
spinoff/contrib/filetransfer/handle.py
spinoff/contrib/filetransfer/request.py
spinoff/contrib/filetransfer/response.py
spinoff/contrib/filetransfer/server.py
spinoff/contrib/filetransfer/tests.py
spinoff/contrib/filetransfer/util.py
spinoff/contrib/http/__init__.py
spinoff/contrib/http/server.py
spinoff/contrib/http/tests.py
spinoff/contrib/monitoring/__init__.py
spinoff/contrib/monitoring/demoapp.py
spinoff/contrib/monitoring/http.py
spinoff/contrib/monitoring/monitor.py
spinoff/contrib/monitoring/static/style.css
spinoff/contrib/monitoring/static/style.scss
spinoff/contrib/monitoring/templates/dashboard.html
spinoff/examples/005_http.py
spinoff/examples/__init__.py
spinoff/examples/example1.py
spinoff/examples/example2.py
spinoff/examples/example2_local.py
spinoff/examples/gevent_example.py
spinoff/remoting/__init__.py
spinoff/remoting/hub.py
spinoff/remoting/hublogic.py
spinoff/remoting/mock.py
spinoff/remoting/noremoting.py
spinoff/remoting/pickler.py
spinoff/remoting/validation.py
spinoff/tests/__init__.py
spinoff/tests/actor_test.py
spinoff/tests/enum_test.py
spinoff/tests/hub_test.py
spinoff/tests/shortcuts_test.py
spinoff/tests/test_events.py
