Metadata-Version: 1.0
Name: spinoff
Version: 0.7.18
Summary: Framework for writing distributed, fault tolerant and scalable internet applications
Home-page: http://github.com/eallik/spinoff/
Author: Erik Allik
Author-email: erik.allik@skype.net
License: BSD
Platform: UNKNOWN
